aws_azuread_login/__init__.py
aws_azuread_login-1.2.dist-info/LICENSE
aws_azuread_login-1.2.dist-info/METADATA
aws_azuread_login-1.2.dist-info/WHEEL
aws_azuread_login-1.2.dist-info/top_level.txt
aws_azuread_login-1.2.dist-info/RECORD
