Metadata-Version: 2.1
Name: aws-azuread-login
Version: 1.2
Summary: Python 3.6+ library to enable programmatic Azure AD auth against AWS
Home-page: https://github.com/david-poirier-csn/aws_azuread_login
Author: David Poirier
Author-email: david-poirier-csn@users.noreply.github.com
License: UNKNOWN
Keywords: azure ad,aws,sso
Platform: UNKNOWN
Classifier: Programming Language :: Python :: 3
Classifier: License :: OSI Approved :: Apache Software License
Classifier: Operating System :: MacOS :: MacOS X
Classifier: Operating System :: POSIX :: Linux
Requires-Python: >= 3.6
Requires-Dist: keyring
Requires-Dist: beautifulsoup4
Requires-Dist: boto3
Requires-Dist: pyppeteer
